{"created_at": "Thu Oct 20 04:10:01 +0000 2011", "favorited": false, "hashtags": ["fuckyoumean", "Pittsburgh", "twitter"], "id": 126872777130123264, "lang": "en", "retweet_count": 3, "retweeted": false, "source": "<a href=\"http://www.tweetcaster.com\" rel=\"nofollow\">TweetCaster for Android</a>", "text": "#fuckyoumean #Pittsburgh don't got the best #twitter.", "truncated": false, "user": {"created_at": "Mon Dec 06 03:31:15 +0000 2010", "description": "My Autobiography - IM THE SHIT...THE END.   #Free Nuttball", "favourites_count": 89, "followers_count": 1720, "friends_count": 1199, "id": 223344460, "lang": "en", "listed_count": 7, "location": "PrettyGirl Trappin -PITTSBURGH", "name": "Ohhsoobadd Monroe", "profile_background_color": "C0DEED", "profile_background_tile": true, "profile_image_url": "https://si0.twimg.com/profile_images/378800000525589577/c8188f18efdbc6340f113e1ed91d19ad_normal.jpeg", "profile_link_color": "0084B4", "profile_sidebar_fill_color": "http://a0.twimg.com/profile_background_images/179148324/zebra_print.gif", "profile_text_color": "333333", "protected": false, "screen_name": "Ohhsoobadd", "statuses_count": 34649, "time_zone": "Quito", "utc_offset": -18000}}
