{"created_at": "Thu Oct 20 04:05:12 +0000 2011", "favorited": false, "hashtags": ["Twitter"], "id": 126871562707144704, "lang": "en", "retweeted": false, "source": "<a href=\"http://www.tweetdeck.com\" rel=\"nofollow\">TweetDeck</a>", "text": "Let's go see what is trending on #Twitter tonight?", "truncated": false, "user": {"created_at": "Wed Jul 29 16:32:13 +0000 2009", "description": "Real Estate Agent w/ Coldwell Banker, Business Man,English & German speaking Agent; Soccer Fan (FC Bayern), & overall Tech Addict! Tweeting about all stuff...", "favourites_count": 223, "followers_count": 2504, "friends_count": 2607, "geo_enabled": true, "id": 61235103, "lang": "en", "listed_count": 61, "location": "\u00dcT: 26.367567,-80.141349", "name": "Steven Bastian", "profile_background_color": "131516", "profile_background_tile": true, "profile_image_url": "https://si0.twimg.com/profile_images/344513261577738080/b824b7910c22d47d0fb9b7c2a4331b3a_normal.jpeg", "profile_link_color": "009999", "profile_sidebar_fill_color": "http://abs.twimg.com/images/themes/theme14/bg.gif", "profile_text_color": "333333", "protected": false, "screen_name": "stevenbastian", "statuses_count": 35249, "time_zone": "Eastern Time (US & Canada)", "url": "http://t.co/kpWilEQ5AC", "utc_offset": -14400}}
